asyncio_contextmanager_pool/__init__.py
asyncio_contextmanager_pool-0.1.2.dist-info/LICENSE
asyncio_contextmanager_pool-0.1.2.dist-info/WHEEL
asyncio_contextmanager_pool-0.1.2.dist-info/METADATA
asyncio_contextmanager_pool-0.1.2.dist-info/RECORD
