Metadata-Version: 2.1
Name: asyncio-contextmanager-pool
Version: 0.1.2
Summary: A library providing a pool-like object for holding `AsyncContextManager` instances.
Home-page: https://github.com/RedRoserade/asyncio-contextmanager-pool
License: MIT
Author: André Carvalho
Author-email: afecarvalho@gmail.com
Requires-Python: >=3.8,<4.0
Classifier: License :: OSI Approved :: MIT License
Classifier: Programming Language :: Python :: 3
Classifier: Programming Language :: Python :: 3.8
Classifier: Programming Language :: Python :: 3.9
Requires-Dist: typing-extensions (>=3.10.0.0); python_version >= "3.8" and python_version < "3.9"
Project-URL: Repository, https://github.com/RedRoserade/asyncio-contextmanager-pool
